<?xml version="1.0" encoding="UTF-8" ?>
<!DOCTYPE mapper PUBLIC "-//mybatis.org//DTD Mapper 3.0//EN" "http://mybatis.org/dtd/mybatis-3-mapper.dtd" >
<mapper namespace="org.hf.jsem.dao.AmMenuMapper" >
  <resultMap id="BaseResultMap" type="org.hf.jsem.entity.AmMenu" >
    <!--
      WARNING - @mbggenerated
      This element is automatically generated by MyBatis Generator, do not modify.
      This element was generated on Mon Oct 31 21:34:23 CST 2016.
    -->
    <id column="menu_id" property="menuId" jdbcType="INTEGER" />
    <result column="menu_name" property="menuName" jdbcType="VARCHAR" />
    <result column="menu_desc" property="menuDesc" jdbcType="VARCHAR" />
    <result column="url" property="url" jdbcType="VARCHAR" />
    <result column="is_group" property="isGroup" jdbcType="VARCHAR" />
    <result column="parent_menu" property="parentMenu" jdbcType="INTEGER" />
    <result column="crt_user" property="crtUser" jdbcType="VARCHAR" />
    <result column="crt_date" property="crtDate" jdbcType="DATE" />
    <result column="last_update_user" property="lastUpdateUser" jdbcType="VARCHAR" />
    <result column="last_update_date" property="lastUpdateDate" jdbcType="TIMESTAMP" />
  </resultMap>
  <resultMap id="ResultMapWithBLOBs" type="org.hf.jsem.entity.AmMenu" extends="BaseResultMap" >
    <!--
      WARNING - @mbggenerated
      This element is automatically generated by MyBatis Generator, do not modify.
      This element was generated on Mon Oct 31 21:34:23 CST 2016.
    -->
    <result column="icon" property="icon" jdbcType="LONGVARCHAR" />
  </resultMap>
  <sql id="Example_Where_Clause" >
    <!--
      WARNING - @mbggenerated
      This element is automatically generated by MyBatis Generator, do not modify.
      This element was generated on Mon Oct 31 21:34:23 CST 2016.
    -->
    <where >
      <foreach collection="oredCriteria" item="criteria" separator="or" >
        <if test="criteria.valid" >
          <trim prefix="(" suffix=")" prefixOverrides="and" >
            <foreach collection="criteria.criteria" item="criterion" >
              <choose >
                <when test="criterion.noValue" >
                  and ${criterion.condition}
                </when>
                <when test="criterion.singleValue" >
                  and ${criterion.condition} #{criterion.value}
                </when>
                <when test="criterion.betweenValue" >
                  and ${criterion.condition} #{criterion.value} and #{criterion.secondValue}
                </when>
                <when test="criterion.listValue" >
                  and ${criterion.condition}
                  <foreach collection="criterion.value" item="listItem" open="(" close=")" separator="," >
                    #{listItem}
                  </foreach>
                </when>
              </choose>
            </foreach>
          </trim>
        </if>
      </foreach>
    </where>
  </sql>
  <sql id="Update_By_Example_Where_Clause" >
    <!--
      WARNING - @mbggenerated
      This element is automatically generated by MyBatis Generator, do not modify.
      This element was generated on Mon Oct 31 21:34:23 CST 2016.
    -->
    <where >
      <foreach collection="example.oredCriteria" item="criteria" separator="or" >
        <if test="criteria.valid" >
          <trim prefix="(" suffix=")" prefixOverrides="and" >
            <foreach collection="criteria.criteria" item="criterion" >
              <choose >
                <when test="criterion.noValue" >
                  and ${criterion.condition}
                </when>
                <when test="criterion.singleValue" >
                  and ${criterion.condition} #{criterion.value}
                </when>
                <when test="criterion.betweenValue" >
                  and ${criterion.condition} #{criterion.value} and #{criterion.secondValue}
                </when>
                <when test="criterion.listValue" >
                  and ${criterion.condition}
                  <foreach collection="criterion.value" item="listItem" open="(" close=")" separator="," >
                    #{listItem}
                  </foreach>
                </when>
              </choose>
            </foreach>
          </trim>
        </if>
      </foreach>
    </where>
  </sql>
  <sql id="Base_Column_List" >
    <!--
      WARNING - @mbggenerated
      This element is automatically generated by MyBatis Generator, do not modify.
      This element was generated on Mon Oct 31 21:34:23 CST 2016.
    -->
    menu_id, menu_name, menu_desc, url, is_group, parent_menu, crt_user, crt_date, last_update_user, 
    last_update_date
  </sql>
  <sql id="Blob_Column_List" >
    <!--
      WARNING - @mbggenerated
      This element is automatically generated by MyBatis Generator, do not modify.
      This element was generated on Mon Oct 31 21:34:23 CST 2016.
    -->
    icon
  </sql>
  <select id="selectByExampleWithBLOBs" resultMap="ResultMapWithBLOBs" parameterType="org.hf.jsem.entity.AmMenuExample" >
    <!--
      WARNING - @mbggenerated
      This element is automatically generated by MyBatis Generator, do not modify.
      This element was generated on Mon Oct 31 21:34:23 CST 2016.
    -->
    select
    <if test="distinct" >
      distinct
    </if>
    <include refid="Base_Column_List" />
    ,
    <include refid="Blob_Column_List" />
    from am_menu
    <if test="_parameter != null" >
      <include refid="Example_Where_Clause" />
    </if>
    <if test="orderByClause != null" >
      order by $orderByClause$
    </if>
  </select>
  <select id="selectByExample" resultMap="BaseResultMap" parameterType="org.hf.jsem.entity.AmMenuExample" >
    <!--
      WARNING - @mbggenerated
      This element is automatically generated by MyBatis Generator, do not modify.
      This element was generated on Mon Oct 31 21:34:23 CST 2016.
    -->
    select
    <if test="distinct" >
      distinct
    </if>
    <include refid="Base_Column_List" />
    from am_menu
    <if test="_parameter != null" >
      <include refid="Example_Where_Clause" />
    </if>
    <if test="orderByClause != null" >
      order by ${orderByClause}
    </if>
  </select>
  <select id="selectByPrimaryKey" resultMap="ResultMapWithBLOBs" parameterType="java.lang.Integer" >
    <!--
      WARNING - @mbggenerated
      This element is automatically generated by MyBatis Generator, do not modify.
      This element was generated on Mon Oct 31 21:34:23 CST 2016.
    -->
    select 
    <include refid="Base_Column_List" />
    ,
    <include refid="Blob_Column_List" />
    from am_menu
    where menu_id = #{menuId,jdbcType=INTEGER}
  </select>
  <delete id="deleteByPrimaryKey" parameterType="java.lang.Integer" >
    <!--
      WARNING - @mbggenerated
      This element is automatically generated by MyBatis Generator, do not modify.
      This element was generated on Mon Oct 31 21:34:23 CST 2016.
    -->
    delete from am_menu
    where menu_id = #{menuId,jdbcType=INTEGER}
  </delete>
  <delete id="deleteByExample" parameterType="org.hf.jsem.entity.AmMenuExample" >
    <!--
      WARNING - @mbggenerated
      This element is automatically generated by MyBatis Generator, do not modify.
      This element was generated on Mon Oct 31 21:34:23 CST 2016.
    -->
    delete from am_menu
    <if test="_parameter != null" >
      <include refid="Example_Where_Clause" />
    </if>
  </delete>
  <insert id="insert" parameterType="org.hf.jsem.entity.AmMenu" >
    <!--
      WARNING - @mbggenerated
      This element is automatically generated by MyBatis Generator, do not modify.
      This element was generated on Mon Oct 31 21:34:23 CST 2016.
    -->
    insert into am_menu (menu_id, menu_name, menu_desc, 
      url, is_group, parent_menu, 
      crt_user, crt_date, last_update_user, 
      last_update_date, icon)
    values (#{menuId,jdbcType=INTEGER}, #{menuName,jdbcType=VARCHAR}, #{menuDesc,jdbcType=VARCHAR}, 
      #{url,jdbcType=VARCHAR}, #{isGroup,jdbcType=VARCHAR}, #{parentMenu,jdbcType=INTEGER}, 
      #{crtUser,jdbcType=VARCHAR}, #{crtDate,jdbcType=DATE}, #{lastUpdateUser,jdbcType=VARCHAR}, 
      #{lastUpdateDate,jdbcType=TIMESTAMP}, #{icon,jdbcType=LONGVARCHAR})
  </insert>
  <insert id="insertSelective" parameterType="org.hf.jsem.entity.AmMenu" >
    <!--
      WARNING - @mbggenerated
      This element is automatically generated by MyBatis Generator, do not modify.
      This element was generated on Mon Oct 31 21:34:23 CST 2016.
    -->
    insert into am_menu
    <trim prefix="(" suffix=")" suffixOverrides="," >
      <if test="menuId != null" >
        menu_id,
      </if>
      <if test="menuName != null" >
        menu_name,
      </if>
      <if test="menuDesc != null" >
        menu_desc,
      </if>
      <if test="url != null" >
        url,
      </if>
      <if test="isGroup != null" >
        is_group,
      </if>
      <if test="parentMenu != null" >
        parent_menu,
      </if>
      <if test="crtUser != null" >
        crt_user,
      </if>
      <if test="crtDate != null" >
        crt_date,
      </if>
      <if test="lastUpdateUser != null" >
        last_update_user,
      </if>
      <if test="lastUpdateDate != null" >
        last_update_date,
      </if>
      <if test="icon != null" >
        icon,
      </if>
    </trim>
    <trim prefix="values (" suffix=")" suffixOverrides="," >
      <if test="menuId != null" >
        #{menuId,jdbcType=INTEGER},
      </if>
      <if test="menuName != null" >
        #{menuName,jdbcType=VARCHAR},
      </if>
      <if test="menuDesc != null" >
        #{menuDesc,jdbcType=VARCHAR},
      </if>
      <if test="url != null" >
        #{url,jdbcType=VARCHAR},
      </if>
      <if test="isGroup != null" >
        #{isGroup,jdbcType=VARCHAR},
      </if>
      <if test="parentMenu != null" >
        #{parentMenu,jdbcType=INTEGER},
      </if>
      <if test="crtUser != null" >
        #{crtUser,jdbcType=VARCHAR},
      </if>
      <if test="crtDate != null" >
        #{crtDate,jdbcType=DATE},
      </if>
      <if test="lastUpdateUser != null" >
        #{lastUpdateUser,jdbcType=VARCHAR},
      </if>
      <if test="lastUpdateDate != null" >
        #{lastUpdateDate,jdbcType=TIMESTAMP},
      </if>
      <if test="icon != null" >
        #{icon,jdbcType=LONGVARCHAR},
      </if>
    </trim>
  </insert>
  <select id="countByExample" parameterType="org.hf.jsem.entity.AmMenuExample" resultType="java.lang.Integer" >
    <!--
      WARNING - @mbggenerated
      This element is automatically generated by MyBatis Generator, do not modify.
      This element was generated on Mon Oct 31 21:34:23 CST 2016.
    -->
    select count(*) from am_menu
    <if test="_parameter != null" >
      <include refid="Example_Where_Clause" />
    </if>
  </select>
  <update id="updateByExampleSelective" parameterType="map" >
    <!--
      WARNING - @mbggenerated
      This element is automatically generated by MyBatis Generator, do not modify.
      This element was generated on Mon Oct 31 21:34:23 CST 2016.
    -->
    update am_menu
    <set >
      <if test="record.menuId != null" >
        menu_id = #{record.menuId,jdbcType=INTEGER},
      </if>
      <if test="record.menuName != null" >
        menu_name = #{record.menuName,jdbcType=VARCHAR},
      </if>
      <if test="record.menuDesc != null" >
        menu_desc = #{record.menuDesc,jdbcType=VARCHAR},
      </if>
      <if test="record.url != null" >
        url = #{record.url,jdbcType=VARCHAR},
      </if>
      <if test="record.isGroup != null" >
        is_group = #{record.isGroup,jdbcType=VARCHAR},
      </if>
      <if test="record.parentMenu != null" >
        parent_menu = #{record.parentMenu,jdbcType=INTEGER},
      </if>
      <if test="record.crtUser != null" >
        crt_user = #{record.crtUser,jdbcType=VARCHAR},
      </if>
      <if test="record.crtDate != null" >
        crt_date = #{record.crtDate,jdbcType=DATE},
      </if>
      <if test="record.lastUpdateUser != null" >
        last_update_user = #{record.lastUpdateUser,jdbcType=VARCHAR},
      </if>
      <if test="record.lastUpdateDate != null" >
        last_update_date = #{record.lastUpdateDate,jdbcType=TIMESTAMP},
      </if>
      <if test="record.icon != null" >
        icon = #{record.icon,jdbcType=LONGVARCHAR},
      </if>
    </set>
    <if test="_parameter != null" >
      <include refid="Update_By_Example_Where_Clause" />
    </if>
  </update>
  <update id="updateByExampleWithBLOBs" parameterType="map" >
    <!--
      WARNING - @mbggenerated
      This element is automatically generated by MyBatis Generator, do not modify.
      This element was generated on Mon Oct 31 21:34:23 CST 2016.
    -->
    update am_menu
    set menu_id = #{record.menuId,jdbcType=INTEGER},
      menu_name = #{record.menuName,jdbcType=VARCHAR},
      menu_desc = #{record.menuDesc,jdbcType=VARCHAR},
      url = #{record.url,jdbcType=VARCHAR},
      is_group = #{record.isGroup,jdbcType=VARCHAR},
      parent_menu = #{record.parentMenu,jdbcType=INTEGER},
      crt_user = #{record.crtUser,jdbcType=VARCHAR},
      crt_date = #{record.crtDate,jdbcType=DATE},
      last_update_user = #{record.lastUpdateUser,jdbcType=VARCHAR},
      last_update_date = #{record.lastUpdateDate,jdbcType=TIMESTAMP},
      icon = #{record.icon,jdbcType=LONGVARCHAR}
    <if test="_parameter != null" >
      <include refid="Update_By_Example_Where_Clause" />
    </if>
  </update>
  <update id="updateByExample" parameterType="map" >
    <!--
      WARNING - @mbggenerated
      This element is automatically generated by MyBatis Generator, do not modify.
      This element was generated on Mon Oct 31 21:34:23 CST 2016.
    -->
    update am_menu
    set menu_id = #{record.menuId,jdbcType=INTEGER},
      menu_name = #{record.menuName,jdbcType=VARCHAR},
      menu_desc = #{record.menuDesc,jdbcType=VARCHAR},
      url = #{record.url,jdbcType=VARCHAR},
      is_group = #{record.isGroup,jdbcType=VARCHAR},
      parent_menu = #{record.parentMenu,jdbcType=INTEGER},
      crt_user = #{record.crtUser,jdbcType=VARCHAR},
      crt_date = #{record.crtDate,jdbcType=DATE},
      last_update_user = #{record.lastUpdateUser,jdbcType=VARCHAR},
      last_update_date = #{record.lastUpdateDate,jdbcType=TIMESTAMP}
    <if test="_parameter != null" >
      <include refid="Update_By_Example_Where_Clause" />
    </if>
  </update>
  <update id="updateByPrimaryKeySelective" parameterType="org.hf.jsem.entity.AmMenu" >
    <!--
      WARNING - @mbggenerated
      This element is automatically generated by MyBatis Generator, do not modify.
      This element was generated on Mon Oct 31 21:34:23 CST 2016.
    -->
    update am_menu
    <set >
      <if test="menuName != null" >
        menu_name = #{menuName,jdbcType=VARCHAR},
      </if>
      <if test="menuDesc != null" >
        menu_desc = #{menuDesc,jdbcType=VARCHAR},
      </if>
      <if test="url != null" >
        url = #{url,jdbcType=VARCHAR},
      </if>
      <if test="isGroup != null" >
        is_group = #{isGroup,jdbcType=VARCHAR},
      </if>
      <if test="parentMenu != null" >
        parent_menu = #{parentMenu,jdbcType=INTEGER},
      </if>
      <if test="crtUser != null" >
        crt_user = #{crtUser,jdbcType=VARCHAR},
      </if>
      <if test="crtDate != null" >
        crt_date = #{crtDate,jdbcType=DATE},
      </if>
      <if test="lastUpdateUser != null" >
        last_update_user = #{lastUpdateUser,jdbcType=VARCHAR},
      </if>
      <if test="lastUpdateDate != null" >
        last_update_date = #{lastUpdateDate,jdbcType=TIMESTAMP},
      </if>
      <if test="icon != null" >
        icon = #{icon,jdbcType=LONGVARCHAR},
      </if>
    </set>
    where menu_id = #{menuId,jdbcType=INTEGER}
  </update>
  <update id="updateByPrimaryKeyWithBLOBs" parameterType="org.hf.jsem.entity.AmMenu" >
    <!--
      WARNING - @mbggenerated
      This element is automatically generated by MyBatis Generator, do not modify.
      This element was generated on Mon Oct 31 21:34:23 CST 2016.
    -->
    update am_menu
    set menu_name = #{menuName,jdbcType=VARCHAR},
      menu_desc = #{menuDesc,jdbcType=VARCHAR},
      url = #{url,jdbcType=VARCHAR},
      is_group = #{isGroup,jdbcType=VARCHAR},
      parent_menu = #{parentMenu,jdbcType=INTEGER},
      crt_user = #{crtUser,jdbcType=VARCHAR},
      crt_date = #{crtDate,jdbcType=DATE},
      last_update_user = #{lastUpdateUser,jdbcType=VARCHAR},
      last_update_date = #{lastUpdateDate,jdbcType=TIMESTAMP},
      icon = #{icon,jdbcType=LONGVARCHAR}
    where menu_id = #{menuId,jdbcType=INTEGER}
  </update>
  <update id="updateByPrimaryKey" parameterType="org.hf.jsem.entity.AmMenu" >
    <!--
      WARNING - @mbggenerated
      This element is automatically generated by MyBatis Generator, do not modify.
      This element was generated on Mon Oct 31 21:34:23 CST 2016.
    -->
    update am_menu
    set menu_name = #{menuName,jdbcType=VARCHAR},
      menu_desc = #{menuDesc,jdbcType=VARCHAR},
      url = #{url,jdbcType=VARCHAR},
      is_group = #{isGroup,jdbcType=VARCHAR},
      parent_menu = #{parentMenu,jdbcType=INTEGER},
      crt_user = #{crtUser,jdbcType=VARCHAR},
      crt_date = #{crtDate,jdbcType=DATE},
      last_update_user = #{lastUpdateUser,jdbcType=VARCHAR},
      last_update_date = #{lastUpdateDate,jdbcType=TIMESTAMP}
    where menu_id = #{menuId,jdbcType=INTEGER}
  </update>
</mapper>